phanim/__init__.py
phanim/animate.py
phanim/camera.py
phanim/color.py
phanim/curve.py
phanim/field.py
phanim/functions.py
phanim/graph.py
phanim/group.py
phanim/particles.py
phanim/phobject.py
phanim/screen.py
phanim/shapes.py
phanim/text.py
phanim/ui.py
phanim-1.0.0.dist-info/METADATA
phanim-1.0.0.dist-info/WHEEL
phanim-1.0.0.dist-info/top_level.txt
phanim-1.0.0.dist-info/RECORD
