Metadata-Version: 2.1
Name: phanim
Version: 1.0.0
Summary: A physics rendering engine
Author-email: Quirijn du Bois <quirijndubois@gmail.com>
Project-URL: Homepage, https://github.com/quirijndubois/phanim
Keywords: render,physics,simulation
Classifier: License :: OSI Approved :: MIT License
Classifier: Programming Language :: Python
Classifier: Programming Language :: Python :: 3
Requires-Python: >=3.9
Requires-Dist: numpy
Requires-Dist: pygame
Requires-Dist: svgpathtools
